[
  {
    "id": "41a3a938-5919-413f-bf06-445574163c29",
    "data": [
      {
        "text": "7890",
        "meta": "@sys.number",
        "alias": "number",
        "userDefined": false
      },
      {
        "text": " is my mobile number",
        "userDefined": false
      }
    ],
    "isTemplate": false,
    "count": 0,
    "lang": "en",
    "updated": 0
  },
  {
    "id": "f26f210e-b46e-4a3a-8bf6-e34365044f78",
    "data": [
      {
        "text": "7890",
        "meta": "@sys.number",
        "alias": "number",
        "userDefined": false
      }
    ],
    "isTemplate": false,
    "count": 0,
    "lang": "en",
    "updated": 0
  },
  {
    "id": "a9fe4d96-6661-42c5-ad78-f979480d45eb",
    "data": [
      {
        "text": "1234",
        "meta": "@sys.number",
        "alias": "number",
        "userDefined": false
      }
    ],
    "isTemplate": false,
    "count": 0,
    "lang": "en",
    "updated": 0
  },
  {
    "id": "3abe6959-2af5-4296-ba1c-4b31e90aa59a",
    "data": [
      {
        "text": "1111",
        "meta": "@sys.number",
        "alias": "number",
        "userDefined": false
      }
    ],
    "isTemplate": false,
    "count": 0,
    "lang": "en",
    "updated": 0
  },
  {
    "id": "4e752935-0338-4924-89c2-5573366b47c7",
    "data": [
      {
        "text": "my phone number is ",
        "userDefined": false
      },
      {
        "text": "999",
        "meta": "@sys.number",
        "alias": "number",
        "userDefined": false
      }
    ],
    "isTemplate": false,
    "count": 0,
    "lang": "en",
    "updated": 0
  }
]